MANIFEST.in
setup.cfg
setup.py
peersub/__init__.py
peersub/peersub.py
peersub.egg-info/PKG-INFO
peersub.egg-info/SOURCES.txt
peersub.egg-info/dependency_links.txt
peersub.egg-info/entry_points.txt
peersub.egg-info/pbr.json
peersub.egg-info/requires.txt
peersub.egg-info/top_level.txt