Metadata-Version: 1.1
Name: peersub
Version: 1.4.0
Summary: Use peerflix with subtitles
Home-page: github.com/walidsa3d/peersub
Author: Walid Saad
Author-email: walid.sa3d@gmail.com
License: MIT
Platform: UNKNOWN
Classifier: Development Status :: 4 - Beta
Classifier: Environment :: Console
Classifier: Intended Audience :: End Users/Desktop
Classifier: License :: OSI Approved :: MIT License
Classifier: Operating System :: Unix
Classifier: Programming Language :: Python :: 2.7
Classifier: Topic :: Utilities
